cocolight/__init__.py
cocolight/_version.py
cocolight/cmodel.py
cocolight/utils.py
cocolight/version.py
cocolight-0.0.3.dist-info/LICENSE.txt
cocolight-0.0.3.dist-info/METADATA
cocolight-0.0.3.dist-info/WHEEL
cocolight-0.0.3.dist-info/top_level.txt
cocolight-0.0.3.dist-info/RECORD
