Metadata-Version: 2.1
Name: cocolight
Version: 0.0.3
Summary: cocoLight: Lightweight cocotb verification library
Author: Kamyar Mohajerani
Author-email: kammoh@gmail.com
License: 
Project-URL: homepage, https://github.com/kammoh/cocolight
Project-URL: repository, https://github.com/kammoh/cocolight.git
Project-URL: changelog, https://github.com/kammoh/cocolight/blob/main/CHANGELOG.md
Keywords: cocotb,HDL,Hardware,verification,VHDL,Verilog,simulation,EDA,FPGA
Classifier: Development Status :: 4 - Beta
Classifier: Programming Language :: Python
Requires-Python: >=3.8
License-File: LICENSE.txt
Requires-Dist: cocotb (>=1.7)
Requires-Dist: attrs (~=22.1)
Requires-Dist: attrs-strict (~=1.0)
Requires-Dist: cffi (>=1.14)
Provides-Extra: test
Requires-Dist: pytest (>7) ; extra == 'test'
Requires-Dist: pytest-cov[all] ; extra == 'test'
